foobot/__init__.py
foobot/api.py
foobot/error.py
foobot-1.0.4.dist-info/DESCRIPTION.rst
foobot-1.0.4.dist-info/METADATA
foobot-1.0.4.dist-info/RECORD
foobot-1.0.4.dist-info/WHEEL
foobot-1.0.4.dist-info/metadata.json
foobot-1.0.4.dist-info/top_level.txt
