Metadata-Version: 2.0
Name: foobot
Version: 1.0.4
Summary: python API wrapper for foobot.io
Home-page: https://github.com/Welltory/python-foobot
Author: Welltory
Author-email: hello@welltory.com
License: BSD
Keywords: air quality,sensor,IoT
Platform: UNKNOWN
Classifier: Intended Audience :: End Users/Desktop
Classifier: Intended Audience :: Developers
Classifier: License :: OSI Approved :: MIT License
Classifier: Operating System :: OS Independent
Classifier: Programming Language :: Python :: 3.4
Requires-Dist: oauth2
Requires-Dist: requests (>=2.7)
